PyFastConfig/__init__.py
PyFastConfig/example.py
PyFastConfig-2.0.dist-info/METADATA
PyFastConfig-2.0.dist-info/WHEEL
PyFastConfig-2.0.dist-info/top_level.txt
PyFastConfig-2.0.dist-info/RECORD
