Metadata-Version: 2.1
Name: PyFastConfig
Version: 2.0
Summary: Fast creation and reading of files on Python with configurations.
Home-page: https://github.com/SuperZombi/PyFastConfig
Author: Super_Zombi
Author-email: super.zombi.yt@gmail.com
License: UNKNOWN
Platform: UNKNOWN
Classifier: Programming Language :: Python :: 3
Classifier: License :: OSI Approved :: MIT License
Classifier: Operating System :: OS Independent
Requires-Python: >=3.6
